cherishbp_kdx/__init__.py
cherishbp_kdx/cherishbp.py
cherishbp_kdx-1.0.dist-info/LICENSE
cherishbp_kdx-1.0.dist-info/METADATA
cherishbp_kdx-1.0.dist-info/WHEEL
cherishbp_kdx-1.0.dist-info/top_level.txt
cherishbp_kdx-1.0.dist-info/RECORD
