Metadata-Version: 2.1
Name: cherishbp_kdx
Version: 1.0
Summary: A Simple BP Neural Network Framework
Author-email: cherish <909956681@qq.com>
Project-URL: Homepage, https://github.com/vkdx/CherishBP
Project-URL: Bug Tracker, https://github.com/vkdx/CherishBP
Classifier: Programming Language :: Python :: 3
Classifier: License :: OSI Approved :: MIT License
Classifier: Operating System :: OS Independent
Requires-Python: >=3.7
License-File: LICENSE
